StickersDownloader/StickersDownloader.py
StickersDownloader/__init__.py
StickersDownloader/__main__.py
stickers_downloader-0.1.10.dist-info/licenses/LICENSE
stickers_downloader-0.1.10.dist-info/METADATA
stickers_downloader-0.1.10.dist-info/WHEEL
stickers_downloader-0.1.10.dist-info/top_level.txt
stickers_downloader-0.1.10.dist-info/RECORD
