Metadata-Version: 2.4
Name: stickers-downloader
Version: 0.1.10
Summary: A Python package to download and convert Telegram animated stickers (TGS) to GIFs.
Author: Ali Ayati Qaffari
Author-email: Ali Ayati Qaffari <ayatiali910@gmail.com>
License-Expression: MIT
Project-URL: Homepage, https://github.com/MrAAQPy/StickersDownloader
Project-URL: Repository, https://github.com/MrAAQPy/StickersDownloader
Project-URL: Issues, https://github.com/MrAAQPy/StickersDownloader/issues
Classifier: Development Status :: 3 - Alpha
Classifier: Intended Audience :: Developers
Classifier: Operating System :: OS Independent
Classifier: Programming Language :: Python :: 3
Classifier: Programming Language :: Python :: 3.7
Classifier: Programming Language :: Python :: 3.8
Classifier: Programming Language :: Python :: 3.9
Classifier: Programming Language :: Python :: 3.10
Classifier: Programming Language :: Python :: 3.11
Classifier: Programming Language :: Python :: 3.12
Classifier: Topic :: Multimedia :: Graphics
Requires-Python: >=3.7
License-File: LICENSE
Requires-Dist: aiohttp>=3.8.0
Requires-Dist: rlottie-python>=1.0.0
Requires-Dist: rich>=13.0.0
Dynamic: license-file
